{
  "required": true,
  "minVersion": "0.7.11",
  "package": "org.kilocraft.essentials.mixin",
  "compatibilityLevel": "JAVA_8",
  "mixins": [
    "EntityMixin",
    "EntitySelectorOptionsMixin",
    "MinecraftDedicatedServerMixin",
    "RconClientMixin",
    "ServerChunkManagerMixin",
    "ServerScoreboardMixin",
    "ServerWorldMixin",
    "SpawnHelperInfoMixin",
    "WorldMixin"
  ],
  "server": [
    "AnvilScreenHandlerMixin",
    "CommandManagerMixin",
    "CraftingScreenHandlerMixin",
    "ForgingScreenHandlerMixin",
    "MinecraftServerMixin",
    "PlayerListS2CPacketMixin",
    "QueryResponseS2CPacketMixin",
    "ServerPlayerEntityMixin",
    "ServerPlayNetworkHandlerMixin"
  ],
  "injectors": {
    "defaultRequire": 1
  }
}
